code_data_extractor/__init__.py
code_data_extractor/extractor.py
code_data_extractor-1.0.14.dist-info/LICENSE
code_data_extractor-1.0.14.dist-info/METADATA
code_data_extractor-1.0.14.dist-info/WHEEL
code_data_extractor-1.0.14.dist-info/top_level.txt
code_data_extractor-1.0.14.dist-info/RECORD
