Metadata-Version: 2.2
Name: code-data-extractor
Version: 1.0.14
Summary: Simple code scanner for static content extraction
Author: casual-aimer
License: GNU GPLv3
Platform: any
Requires-Python: >=3.9
License-File: LICENSE
Requires-Dist: simplemma<2.0.0,>=1.1.0
Requires-Dist: libcst<2.0.0,>=1.4.0
Requires-Dist: nltk<4.0.0,>=3.9.0
Dynamic: author
Dynamic: description
Dynamic: description-content-type
Dynamic: license
Dynamic: platform
Dynamic: requires-dist
Dynamic: requires-python
Dynamic: summary
